[
   {
       "id": 1,
       "name": "Fjallraven - Foldsack No. 1 Backpack, Fits 15 Laptops",
       "src": "/images/categor"
   },
   {
       "id": 2,
       "name": "Mens Casual Premium Slim Fit T-Shirts ",
       "src": "/images/categor"
   },
   {
       "id": 3,
       "name": "Mens Cotton Jacket",
       "src": "/images/categor"
   },
   {
       "id": 4,
       "name": "Mens Casual Slim Fit",
       "src": "/images/categor"
   },
   {
       "id": 5,
       "name": "John Hardy Women's Legends Naga Gold & Silver Dragon Station Chain Bracelet",
       "src": "/images/categor"
   },
   {
       "id": 6,
       "name": "Solid Gold Petite Micropave ",
       "src": "/images/categor"
   },
   {
       "id": 7,
       "name": "White Gold Plated Princess",
       "src": "/images/categor"
   },
   {
       "id": 8,
       "name": "Pierced Owl Rose Gold Plated Stainless Steel Double",
       "src": "/images/categor"
   },
   {
       "id": 9,
       "name": "WD 2TB Elements Portable External Hard Drive - USB 3.0 ",
       "src": "/images/categor"
   },
   {
       "id": 10,
       "name": "SanDisk SSD PLUS 1TB Internal SSD - SATA III 6 Gb/s",
       "src": "/images/categor"
   },
   {
       "id": 11,
       "name": "Silicon Power 256GB SSD 3D NAND A55 SLC Cache Performance Boost SATA III 2.5",
       "src": "/images/categor"
   },
   {
       "id": 12,
       "name": "WD 4TB Gaming Drive Works with Playstation 4 Portable External Hard Drive",
       "src": "/images/categor"
   },
   {
       "id": 13,
       "name": "Acer SB220Q bi 21.5 inches Full HD (1920 x 1080) IPS Ultra-Thin",
       "src": "/images/categor"
   },
   {
       "id": 14,
       "name": "Samsung 49-Inch CHG90 144Hz Curved Gaming Monitor (LC49HG90DMNXZA) – Super Ultrawide Screen QLED ",
       "src": "/images/categor"
   },
   {
       "id": 15,
       "name": "BIYLACLESEN Women's 3-in-1 Snowboard Jacket Winter Coats",
       "src": "/images/categor"
   },
   {
       "id": 16,
       "name": "Lock and Love Women's Removable Hooded Faux Leather Moto Biker Jacket",
       "src": "/images/categor"
   },
   {
       "id": 17,
       "name": "Rain Jacket Women Windbreaker Striped Climbing Raincoats",
       "src": "/images/categor"
   },
   {
       "id": 18,
       "name": "MBJ Women's Solid Short Sleeve Boat Neck V ",
       "src": "/images/categor"
   },
   {
       "id": 19,
       "name": "Opna Women's Short Sleeve Moisture",
       "src": "/images/categor"
   },
   {
       "id": 20,
       "name": "DANVOUY Womens T Shirt Casual Cotton Short",
       "src": "/images/categor"
   }
]